reloadium_launcher.py
reloadium/__init__.py
reloadium/__main__.py
reloadium/__utils__.py
reloadium/__version__.py
reloadium/lib/__init__.py
reloadium/lib/environ.py
reloadium/lib/extensions/__init__.py
reloadium/lib/extensions/django.py
reloadium/lib/extensions/extension.py
reloadium/lib/extensions/fastapi.py
reloadium/lib/extensions/flask.py
reloadium/lib/extensions/graphene.py
reloadium/lib/extensions/manager.py
reloadium/lib/extensions/multiprocessing.py
reloadium/lib/extensions/numba.py
reloadium/lib/extensions/pandas.py
reloadium/lib/extensions/pygame.py
reloadium/lib/extensions/pytest.py
reloadium/lib/extensions/pytest_extension_guard.py
reloadium/lib/extensions/server_extension.py
reloadium/lib/extensions/sqlalchemy.py
reloadium/lib/extensions_raw/__init__.py
reloadium/lib/extensions_raw/multiprocessing.py
reloadium/lib/fr/__init__.py
reloadium/lib/fr/handlers.py
reloadium/vendored/__init__.py
reloadium/vendored/semantic_version.py
reloadium/vendored/types.py
reloadium/vendored/typing_extensions.py
reloadium/vendored/websocket_server.py
reloadium/vendored/asgiref/__init__.py
reloadium/vendored/asgiref/compatibility.py
reloadium/vendored/asgiref/current_thread_executor.py
reloadium/vendored/asgiref/local.py
reloadium/vendored/asgiref/py.typed
reloadium/vendored/asgiref/server.py
reloadium/vendored/asgiref/sync.py
reloadium/vendored/asgiref/testing.py
reloadium/vendored/asgiref/timeout.py
reloadium/vendored/asgiref/typing.py
reloadium/vendored/envium/__init__.py
reloadium/vendored/envium/ctx.py
reloadium/vendored/envium/environ.py
reloadium/vendored/envium/exceptions.py
reloadium/vendored/envium/py.typed
reloadium/vendored/envium/secrets.py
reloadium/vendored/envium/vars.py
reloadium/vendored/globmatch/__init__.py
reloadium/vendored/globmatch/_version.py
reloadium/vendored/globmatch/pathutils.py
reloadium/vendored/globmatch/translation.py
reloadium/vendored/pkg_resources/__init__.py
reloadium/vendored/pkg_resources/_vendor/__init__.py
reloadium-1.5.1.dist-info/METADATA
reloadium-1.5.1.dist-info/WHEEL
reloadium-1.5.1.dist-info/entry_points.txt
reloadium-1.5.1.dist-info/top_level.txt
reloadium-1.5.1.dist-info/RECORD
