Metadata-Version: 2.1
Name: reloadium
Version: 1.5.1
Summary: Hot reloader aka edit and continue for Python
Home-page: https://github.com/reloadware/reloadium
Author: Reloadware
Author-email: damian@reloadware.com
Requires-Python: >=3.7.0,<4.0
